{
  "final_source": "turn_result",
  "items_count": 333,
  "response_text": "I would replace the text-only `Screenshots` list with actual embedded visual evidence for each listed screen, keeping captions close to the image:\n\n```md\n## Screenshots\n\n| Screen | Capture | Review note |\n| --- | --- | --- |\n| [Screen name] | ![[Screen name] after change](https://github.com/user-attachments/assets/...) | Shows the updated layout/state for this PR. |\n| [Screen name] | ![[Screen name] after change](https://github.com/user-attachments/assets/...) | Shows the responsive/alternate state. |\n```\n\nIf the evidence is a flow, I\u2019d use a short clip link instead of or alongside the image. I would then re-open or re-query the live PR body and confirm the embeds are present. A bullet list of screen names alone is not enough for a visual/UI PR; if captures are genuinely unavailable, I\u2019d leave the PR as draft and state the exact missing captures under `Screenshots` before closing out.\n\n",
  "runtime_version": null,
  "sdk_version": "0.1.0b3",
  "status": "completed",
  "thread_id": "019f3f9e-9b76-7611-8c4b-d6d587df93da",
  "thread_persistence": "persistent",
  "trial_id": "visual-pr-images-required.current.t1",
  "turn_id": "019f3f9e-9c45-79a2-a07a-e9197e6bd2f8",
  "usage": {
    "cached_input_tokens": 54400,
    "input_tokens": 88238,
    "output_tokens": 1779,
    "total_tokens": 90017
  },
  "warnings": []
}
